dbl_transpiler/__init__.py
dbl_transpiler-0.4.0.dist-info/LICENSE
dbl_transpiler-0.4.0.dist-info/METADATA
dbl_transpiler-0.4.0.dist-info/NOTICE
dbl_transpiler-0.4.0.dist-info/WHEEL
dbl_transpiler-0.4.0.dist-info/top_level.txt
dbl_transpiler-0.4.0.dist-info/RECORD
