Metadata-Version: 2.1
Name: dbl-transpiler
Version: 0.4.0
Summary: SIEM-to-PySpark Transpiler
Home-page: https://github.com/databrickslabs/transpiler
Author: Databricks Labs
Author-email: UNKNOWN
License: Databricks License
Platform: UNKNOWN
Classifier: Programming Language :: Python :: 3
Classifier: License :: Other/Proprietary License
Classifier: Operating System :: OS Independent
